pwnenv/__init__.py
pwnenv/utils.py
pwnenv-0.21.dist-info/LICENSE
pwnenv-0.21.dist-info/METADATA
pwnenv-0.21.dist-info/WHEEL
pwnenv-0.21.dist-info/top_level.txt
pwnenv-0.21.dist-info/RECORD
